riskoptimix/__init__.py
riskoptimix/data.py
riskoptimix/exceptions.py
riskoptimix/indicators.py
riskoptimix-0.1.0.dist-info/licenses/LICENSE
riskoptimix-0.1.0.dist-info/METADATA
riskoptimix-0.1.0.dist-info/WHEEL
riskoptimix-0.1.0.dist-info/top_level.txt
riskoptimix-0.1.0.dist-info/RECORD
