Metadata-Version: 2.4
Name: riskoptimix
Version: 0.1.0
Summary: A simple Python toolkit for algorithmic trading
Author-email: Thomas van der Hulst <riskoptimix@gmail.com>
License: MIT
Project-URL: Homepage, https://github.com/ThomasvdHulst/riskoptimix
Project-URL: Bug Tracker, https://github.com/ThomasvdHulst/riskoptimix/issues
Project-URL: Documentation, https://github.com/ThomasvdHulst/riskoptimix#readme
Keywords: trading,finance,algorithmic-trading,technical-analysis,backtesting
Classifier: Development Status :: 3 - Alpha
Classifier: Intended Audience :: Developers
Classifier: Intended Audience :: Financial and Insurance Industry
Classifier: License :: OSI Approved :: MIT License
Classifier: Operating System :: OS Independent
Classifier: Programming Language :: Python :: 3
Classifier: Programming Language :: Python :: 3.8
Classifier: Programming Language :: Python :: 3.9
Classifier: Programming Language :: Python :: 3.10
Classifier: Programming Language :: Python :: 3.11
Classifier: Topic :: Office/Business :: Financial :: Investment
Requires-Python: >=3.8
License-File: LICENSE
Requires-Dist: pandas>=1.5.0
Requires-Dist: numpy>=1.20.0
Requires-Dist: yfinance>=0.2.0
Requires-Dist: requests>=2.28.0
Provides-Extra: dev
Requires-Dist: pytest>=7.0.0; extra == "dev"
Requires-Dist: pytest-cov>=4.0.0; extra == "dev"
Requires-Dist: black>=22.0.0; extra == "dev"
Requires-Dist: flake8>=5.0.0; extra == "dev"
Requires-Dist: isort>=5.0.0; extra == "dev"
Requires-Dist: mypy>=0.990; extra == "dev"
Dynamic: license-file
